oldaicsimageio/__init__.py
oldaicsimageio/aicsImage.py
oldaicsimageio/aicsimageio_version.py
oldaicsimageio/checkForOmeTif.py
oldaicsimageio/cziReader.py
oldaicsimageio/czifile.py
oldaicsimageio/exceptions.py
oldaicsimageio/omeTifReader.py
oldaicsimageio/omeTifWriter.py
oldaicsimageio/omexml.py
oldaicsimageio/pngReader.py
oldaicsimageio/pngWriter.py
oldaicsimageio/tifReader.py
oldaicsimageio/typeChecker.py
oldaicsimageio/version.py
oldaicsimageio-0.6.6.dist-info/LICENSE.txt
oldaicsimageio-0.6.6.dist-info/METADATA
oldaicsimageio-0.6.6.dist-info/WHEEL
oldaicsimageio-0.6.6.dist-info/entry_points.txt
oldaicsimageio-0.6.6.dist-info/top_level.txt
oldaicsimageio-0.6.6.dist-info/RECORD
