Metadata-Version: 2.1
Name: oldaicsimageio
Version: 0.6.6
Summary: A generalized scientific image processing module from the Allen Institute for Cell Science.
Home-page: UNKNOWN
Author: AICS
Author-email: !AICS_SW@alleninstitute.org
License: Allen Institute Software License
Platform: UNKNOWN
Requires-Dist: imageio (>=2.3.0)
Requires-Dist: numpy (>=1.14.5)
Requires-Dist: Pillow (>=5.2.0)
Requires-Dist: scipy (>=1.1.0)
Requires-Dist: matplotlib (>=2.2.2)
Requires-Dist: scikit-image (>=0.14.0)
Requires-Dist: tifffile (==0.15.1)
Provides-Extra: interactive_dev_group
Provides-Extra: lint_group
Requires-Dist: flake8 ; extra == 'lint_group'
Provides-Extra: test_group
Requires-Dist: pytest ; extra == 'test_group'
Requires-Dist: pytest-cov ; extra == 'test_group'
Requires-Dist: pytest-raises ; extra == 'test_group'
